tripsweb/__init__.py
tripsweb/inputterms.py
tripsweb/process.py
tripsweb/query.py
trips_web-1.0.11.dist-info/METADATA
trips_web-1.0.11.dist-info/WHEEL
trips_web-1.0.11.dist-info/entry_points.txt
trips_web-1.0.11.dist-info/top_level.txt
trips_web-1.0.11.dist-info/RECORD
